{
    "key": "group_654959b609594",
    "title": "Block: Tabs (Site Settings)",
    "fields": [
        {
            "key": "field_656f879ccf605",
            "label": "Styles",
            "name": "tabs_block_styles",
            "aria-label": "",
            "type": "repeater",
            "instructions": "",
            "required": 0,
            "conditional_logic": 0,
            "wrapper": {
                "width": "",
                "class": "",
                "id": ""
            },
            "acfe_repeater_stylised_button": 0,
            "layout": "table",
            "pagination": 0,
            "min": 0,
            "max": 0,
            "collapsed": "",
            "button_label": "Add Row",
            "rows_per_page": 20,
            "sub_fields": [
                {
                    "key": "field_656f879ccf606",
                    "label": "Style Name",
                    "name": "style_name",
                    "aria-label": "",
                    "type": "acfe_slug",
                    "instructions": "",
                    "required": 0,
                    "conditional_logic": 0,
                    "wrapper": {
                        "width": "",
                        "class": "",
                        "id": ""
                    },
                    "default_value": "",
                    "placeholder": "",
                    "prepend": "",
                    "append": "",
                    "maxlength": "",
                    "parent_repeater": "field_656f879ccf605"
                }
            ]
        },
        {
            "key": "field_654959b6163da",
            "label": "Global Settings",
            "name": "tabs_block_global",
            "aria-label": "",
            "type": "group",
            "instructions": "",
            "required": 0,
            "conditional_logic": 0,
            "wrapper": {
                "width": "",
                "class": "",
                "id": ""
            },
            "layout": "block",
            "acfe_seamless_style": 0,
            "acfe_group_modal": 0,
            "acfe_group_modal_close": 0,
            "acfe_group_modal_button": "",
            "acfe_group_modal_size": "large",
            "sub_fields": [
                {
                    "key": "field_654959b61e2dc",
                    "label": "Heading Style",
                    "name": "heading_style",
                    "aria-label": "",
                    "type": "button_group",
                    "instructions": "Select the heading level for the heading text (default: H3)",
                    "required": 0,
                    "conditional_logic": 0,
                    "wrapper": {
                        "width": "",
                        "class": "",
                        "id": ""
                    },
                    "hide_field": "",
                    "hide_label": "",
                    "hide_instructions": "",
                    "hide_required": "",
                    "choices": {
                        "h1": "H1",
                        "h2": "H2",
                        "h3": "H3",
                        "h4": "H4",
                        "h5": "H5",
                        "h6": "H6"
                    },
                    "default_value": "h3",
                    "return_format": "value",
                    "acfe_settings": "",
                    "acfe_validate": "",
                    "allow_null": 0,
                    "instruction_placement": "tooltip",
                    "acfe_permissions": "",
                    "layout": "horizontal"
                },
                {
                    "key": "field_654959b61e38c",
                    "label": "Browser History",
                    "name": "browser_history",
                    "aria-label": "",
                    "type": "button_group",
                    "instructions": "Set to Yes to track tab open in browser history (default: No)",
                    "required": 0,
                    "conditional_logic": 0,
                    "wrapper": {
                        "width": "",
                        "class": "",
                        "id": ""
                    },
                    "hide_field": "",
                    "hide_label": "",
                    "hide_instructions": "",
                    "hide_required": "",
                    "choices": {
                        "y": "Yes",
                        "n": "No"
                    },
                    "default_value": "n",
                    "return_format": "value",
                    "acfe_settings": "",
                    "acfe_validate": "",
                    "allow_null": 0,
                    "instruction_placement": "tooltip",
                    "acfe_permissions": "",
                    "layout": "horizontal"
                },
                {
                    "key": "field_654959b61e256",
                    "label": "Convert to Accordion",
                    "name": "convert_to_accordion",
                    "aria-label": "",
                    "type": "checkbox",
                    "instructions": "Select the screen sizes where the tabs will convert to accordions (default: none)",
                    "required": 0,
                    "conditional_logic": 0,
                    "wrapper": {
                        "width": "",
                        "class": "",
                        "id": ""
                    },
                    "hide_field": "",
                    "hide_label": "",
                    "hide_instructions": "",
                    "hide_required": "",
                    "choices": {
                        "xs": "XS",
                        "sm": "SM"
                    },
                    "default_value": [],
                    "return_format": "value",
                    "min": "",
                    "max": "",
                    "acfe_settings": "",
                    "acfe_validate": "",
                    "allow_custom": 0,
                    "instruction_placement": "tooltip",
                    "acfe_permissions": "",
                    "layout": "horizontal",
                    "toggle": 1,
                    "save_custom": 0,
                    "custom_choice_button_text": "Add new choice"
                },
                {
                    "key": "field_654959b61e4ec",
                    "label": "Auto Scroll",
                    "name": "auto_scroll",
                    "aria-label": "",
                    "type": "checkbox",
                    "instructions": "Select the screen sizes where auto-scroll will be enabled (default: none)",
                    "required": 0,
                    "conditional_logic": 0,
                    "wrapper": {
                        "width": "",
                        "class": "",
                        "id": ""
                    },
                    "hide_field": "",
                    "hide_label": "",
                    "hide_instructions": "",
                    "hide_required": "",
                    "choices": {
                        "xs": "XS",
                        "sm": "SM",
                        "md": "MD",
                        "lg": "LG",
                        "xl": "XL"
                    },
                    "default_value": [],
                    "return_format": "value",
                    "min": "",
                    "max": "",
                    "acfe_settings": "",
                    "acfe_validate": "",
                    "allow_custom": 0,
                    "instruction_placement": "tooltip",
                    "acfe_permissions": "",
                    "layout": "horizontal",
                    "toggle": 1,
                    "save_custom": 0,
                    "custom_choice_button_text": "Add new choice"
                }
            ]
        },
        {
            "key": "field_656f87e9ef853",
            "label": "Presets",
            "name": "tabs_block_presets",
            "aria-label": "",
            "type": "repeater",
            "instructions": "",
            "required": 0,
            "conditional_logic": 0,
            "wrapper": {
                "width": "",
                "class": "",
                "id": ""
            },
            "acfe_repeater_stylised_button": 0,
            "layout": "block",
            "pagination": 0,
            "min": 0,
            "max": 0,
            "collapsed": "field_656f87fcef854",
            "button_label": "Add Row",
            "rows_per_page": 20,
            "sub_fields": [
                {
                    "key": "field_656f87fcef854",
                    "label": "Preset Name",
                    "name": "preset_name",
                    "aria-label": "",
                    "type": "acfe_slug",
                    "instructions": "",
                    "required": 0,
                    "conditional_logic": 0,
                    "wrapper": {
                        "width": "",
                        "class": "",
                        "id": ""
                    },
                    "default_value": "",
                    "placeholder": "",
                    "prepend": "",
                    "append": "",
                    "maxlength": "",
                    "parent_repeater": "field_656f87e9ef853"
                },
                {
                    "key": "field_656f8808ef855",
                    "label": "",
                    "name": "",
                    "aria-label": "",
                    "type": "clone",
                    "instructions": "",
                    "required": 0,
                    "conditional_logic": 0,
                    "wrapper": {
                        "width": "",
                        "class": "",
                        "id": ""
                    },
                    "clone": [
                        "group_656f861450063"
                    ],
                    "display": "seamless",
                    "layout": "block",
                    "prefix_label": 0,
                    "prefix_name": 0,
                    "acfe_seamless_style": 0,
                    "acfe_clone_modal": 0,
                    "acfe_clone_modal_close": 0,
                    "acfe_clone_modal_button": "",
                    "acfe_clone_modal_size": "large",
                    "parent_repeater": "field_656f87e9ef853"
                }
            ]
        }
    ],
    "location": [
        [
            {
                "param": "options_page",
                "operator": "==",
                "value": "tabs"
            }
        ]
    ],
    "menu_order": 0,
    "position": "normal",
    "style": "default",
    "label_placement": "top",
    "instruction_placement": "label",
    "hide_on_screen": "",
    "active": true,
    "description": "",
    "show_in_rest": 0,
    "acfe_autosync": [
        "json"
    ],
    "acfe_form": 1,
    "acfe_display_title": "",
    "acfe_permissions": "",
    "acfe_meta": "",
    "acfe_note": "",
    "modified": 1718724373
}
